runperf/__init__.py
runperf/exceptions.py
runperf/html_report.py
runperf/machine.py
runperf/profiles.py
runperf/provisioners.py
runperf/result.py
runperf/tests.py
runperf/version.py
runperf/assets/pbench-agent.cfg
runperf/assets/html_report/report_template.html
runperf/assets/html_report/report_template.html.variables
runperf/assets/pbench/nbd-check.fio
runperf/assets/pbench/nbd.fio
runperf/assets/profiles/TunedLibvirt/rc.local.sh
runperf/assets/tests/DummyTest/result.json
runperf/utils/__init__.py
runperf/utils/cloud_image_providers.py
runperf/utils/pbench.py
runperf-1.1.data/scripts/analyze-perf
runperf-1.1.data/scripts/compare-perf
runperf-1.1.data/scripts/diff-perf
runperf-1.1.data/scripts/run-perf
runperf-1.1.data/scripts/strip-run-perf
runperf-1.1.dist-info/LICENSE
runperf-1.1.dist-info/METADATA
runperf-1.1.dist-info/WHEEL
runperf-1.1.dist-info/entry_points.txt
runperf-1.1.dist-info/top_level.txt
runperf-1.1.dist-info/RECORD
