Metadata-Version: 2.1
Name: runperf
Version: 1.1
Summary: Helper to execute perf-beaker-tasks locally or in VM
Home-page: https://github.com/distributed-system-analysis/run-perf
Author: Lukas Doktor
Author-email: ldoktor@redhat.com
License: GPLv2+
Platform: UNKNOWN
Classifier: Development Status :: 4 - Beta
Classifier: Intended Audience :: Developers
Classifier: License :: OSI Approved :: GNU General Public License v2 or later (GPLv2+)
Classifier: Natural Language :: English
Classifier: Operating System :: POSIX
Classifier: Topic :: Software Development :: Quality Assurance
Classifier: Topic :: Software Development :: Testing
Classifier: Programming Language :: Python :: 3
Requires-Python: >=3.4
License-File: LICENSE
Requires-Dist: aexpect (>=1.5.1)
Requires-Dist: PyYAML
Requires-Dist: numpy
